{"active":[{"name":"\u7238\u7238\u53bb\u54ea\u513f","href":"#!\/","img":"http:\/\/gtms01.alicdn.com\/tps\/i1\/T1feSSXj8yXXb1upjX.jpg","banner":"http:\/\/gtms01.alicdn.com\/tps\/i1\/T101ffXgpwXXb1upjX.jpg","sec":[{"name":"\u5965\u7279\u66fc\u86cb","href":"#!search\/%E5%A5%A5%E7%89%B9%E6%9B%BC%E8%9B%8B\/cat%3D52344001\/","img":"http:\/\/gtms01.alicdn.com\/tps\/i1\/T1kRHdXnFvXXb1upjX.jpg"},{"name":"kimi\u65c5\u884c\u7bb1","href":"#!search\/%E7%88%B8%E7%88%B8%E5%8E%BB%E5%93%AA%E5%84%BF%20%E9%97%AA%E7%94%B5%E9%BA%A6%E6%98%86%E6%8B%89%E6%9D%86%E7%AE%B1\/\/","img":"http:\/\/gtms01.alicdn.com\/tps\/i1\/T1BeYiXbBuXXb1upjX.jpg"},{"name":"kimi\u8d85\u4eba\u7761\u8863","href":"#!search\/kimi%20%E8%B6%85%E4%BA%BA%20%E7%9D%A1%E8%A1%A3\/\/","img":"http:\/\/gtms01.alicdn.com\/tps\/i1\/T1qpTaXnhtXXb1upjX.jpg"},{"name":"angela\u4eb2\u5b50\u88c5","href":"#!search\/%E7%88%B8%E7%88%B8%E5%8E%BB%E5%93%AA%E5%84%BF%20angela%E4%BA%B2%E5%AD%90%E8%A3%85\/\/","img":"http:\/\/gtms01.alicdn.com\/tps\/i1\/T1_x.cXflkXXb1upjX.jpg"},{"name":"kimi\u5fc3\u7231\u5c0f\u9ec4","href":"#!search\/kimi%20%E5%B0%8F%E9%BB%84\/\/","img":"http:\/\/gtms01.alicdn.com\/tps\/i1\/T1_x.cXflkXXb1upjX.jpg"},{"name":"kimi\u8ff7\u5f69\u9a6c\u7532","href":"#!search\/kimi%20%E8%BF%B7%E5%BD%A9%E9%A9%AC%E7%94%B2\/cat%3D52290018\/","img":"http:\/\/gtms01.alicdn.com\/tps\/i1\/T1_x.cXflkXXb1upjX.jpg"}]},{"name":"\u8fa3\u5988\u795e\u5668","href":"#!\/","img":"http:\/\/gtms01.alicdn.com\/tps\/i1\/T1HoySXkNCXXb1upjX.jpg","banner":"","sec":[{"name":"\u5988\u5988\u5916\u51fa","href":"#!search\/%E5%AD%95%E5%A6%87%E7%BE%BD%E7%BB%92\/cat%3D52392004\/","img":""},{"name":"\u5b9d\u5b9d\u5916\u51fa","href":"#!search\/%E5%84%BF%E7%AB%A5%E7%BE%BD%E7%BB%92%E6%9C%8D\/cat%3D52290018\/","img":""},{"name":"\u5b55\u4ea7\u5987\u978b\u5b50","href":"#!search\/%E5%AD%95%E5%A6%87%E9%9E%8B\/cat%3D52372005\/","img":""},{"name":"\u5b9d\u5b9d\u9774\u5b50","href":"#!search\/%E5%AE%9D%E5%AE%9D%E9%9D%B4%E5%AD%90\/cat%3D52290018\/","img":""},{"name":"\u6f02\u4eae\u5988\u5988","href":"#!search\/%E8%A1%A5%E6%B0%B4\/cat%3D52372005\/","img":""},{"name":"\u6f02\u4eae\u5b9d\u5b9d","href":"#!search\/%E6%B6%A6%E8%82%A4\/cat%3D52398006\/","img":""},{"name":"\u5988\u5988\u5c45\u5bb6","href":"#!search\/%E6%9C%88%E5%AD%90%E6%9C%8D\/cat%3D52372005\/","img":""},{"name":"\u5b9d\u5b9d\u5185\u8863","href":"#!search\/%E4%BF%9D%E6%9A%96%E5%86%85%E8%A1%A3\/cat%3D52290018\/","img":""},{"name":"\u5b55\u5987\u6258\u8179\u88e4","href":"#!search\/%E6%89%98%E8%85%B9%E8%A3%A4\/cat%3D52392004\/","img":""},{"name":"\u5b9d\u5b9d\u5e3d\u5b50","href":"#!search\/%E5%B8%BD%E5%AD%90\/cat%3D52290018\/","img":""}]},{"name":"\u7238\u7238\u53bb\u54ea\u513f\u5566","href":"#!search\/%E9%9B%AA%E5%9C%B0%E9%9D%B4\/cat%3D52346001\/","img":"http:\/\/gtms01.alicdn.com\/tps\/i1\/T16BmPXgNAXXb1upjX.jpg","banner":"","sec":[]},{"name":"\u5962\u534e\u6bdb\u5462","href":"#!search\/%E6%AF%9B%E5%91%A2\/cat%3D52398008\/","img":"http:\/\/gtms01.alicdn.com\/tps\/i1\/T14bKWXeBvXXb1upjX.jpg","banner":"","sec":[]}],"cat":[{"name":"\u5973\u88c5","img":"http:\/\/gtms01.alicdn.com\/tps\/i1\/T1jaI9FiheXXb1upjX.jpg"},{"name":"\u5973\u978b","img":"http:\/\/gtms01.alicdn.com\/tps\/i1\/T1mnE9FeXeXXb1upjX.jpg"},{"name":"\u7f8e\u5986","img":"http:\/\/gtms01.alicdn.com\/tps\/i1\/T1YYtaFBNcXXb1upjX.jpg"},{"name":"\u7537\u88c5","img":"http:\/\/gtms01.alicdn.com\/tps\/i1\/T1hvNXFz0dXXb1upjX.jpg"},{"name":"\u7537\u978b","img":"http:\/\/gtms01.alicdn.com\/tps\/i1\/T1Lq0jFplaXXb1upjX.jpg"},{"name":"\u6237\u5916\u8fd0\u52a8","img":"http:\/\/gtms01.alicdn.com\/tps\/i1\/T1thXhFtBbXXb1upjX.jpg"},{"name":"\u7bb1\u5305","img":"http:\/\/gtms01.alicdn.com\/tps\/i1\/T1MgVeFqRbXXb1upjX.jpg"},{"name":"\u914d\u9970","img":"http:\/\/gtms01.alicdn.com\/tps\/i1\/T1a.leFp0bXXb1upjX.jpg"},{"name":"\u5185\u8863","img":"http:\/\/gtms01.alicdn.com\/tps\/i1\/T1HjBdFptbXXb1upjX.jpg"},{"name":"\u624b\u673a\u6570\u7801","img":"http:\/\/gtms01.alicdn.com\/tps\/i1\/T1XpJlFv8XXXb1upjX.jpg"},{"name":"\u5bb6\u7528\u7535\u5668","img":"http:\/\/gtms01.alicdn.com\/tps\/i1\/T1LzBbFrxcXXb1upjX.jpg"},{"name":"\u6c7d\u8f66\u7528\u54c1","img":"http:\/\/gtms01.alicdn.com\/tps\/i1\/T1oUxkFvJXXXb1upjX.jpg"},{"name":"\u7ae5\u88c5","img":"http:\/\/gtms01.alicdn.com\/tps\/i1\/T1CWJdFxJbXXb1upjX.jpg"},{"name":"\u73a9\u5177","img":"http:\/\/gtms01.alicdn.com\/tps\/i1\/T1ReddFzNbXXb1upjX.jpg"},{"name":"\u6bcd\u5a74","img":"http:\/\/gtms01.alicdn.com\/tps\/i1\/T1XgrmXeXtXXb1upjX.jpg"},{"name":"\u65e5\u7528\u767e\u8d27","img":"http:\/\/gtms01.alicdn.com\/tps\/i1\/T1dFbrXatwXXb1upjX.jpg"},{"name":"\u98df\u54c1\u996e\u6599","img":"http:\/\/gtms01.alicdn.com\/tps\/i1\/T1BqA9FeteXXb1upjX.jpg"},{"name":"\u53a8\u623f\u7528\u5177","img":"http:\/\/gtms01.alicdn.com\/tps\/i1\/T1z.s9FfdeXXb1upjX.jpg"},{"name":"\u56fe\u4e66\u97f3\u50cf","img":"http:\/\/gtms01.alicdn.com\/tps\/i1\/T1o14XFqFdXXb1upjX.jpg"},{"name":"\u5ba0\u7269","img":"http:\/\/gtms01.alicdn.com\/tps\/i1\/T1yaXgFqVdXXb1upjX.jpg"},{"name":"\u5bb6\u5177\u5efa\u6750","img":"http:\/\/gtms01.alicdn.com\/tps\/i1\/T1bb4fFENaXXb1upjX.jpg"},{"name":"\u533b\u7597\u4fdd\u5065","img":"http:\/\/gtms01.alicdn.com\/tps\/i1\/T1rBGOXa4wXXb1upjX.jpg"},{"name":"\u6587\u5a31\u529e\u516c","img":"http:\/\/gtms01.alicdn.com\/tps\/i1\/T1e8SSXc4yXXb1upjX.jpg"}]}